{
    "id": "3eb3d1b6-26fb-453f-ba50-796d900a826d",
    "prevId": "00000000-0000-0000-0000-000000000000",
    "version": "7",
    "dialect": "postgresql",
    "tables": {
        "public.provinces": {
            "name": "provinces",
            "schema": "",
            "columns": {
                "id": {
                    "name": "id",
                    "type": "serial",
                    "primaryKey": true,
                    "notNull": true
                },
                "color": {
                    "name": "color",
                    "type": "text",
                    "primaryKey": false,
                    "notNull": true
                },
                "type": {
                    "name": "type",
                    "type": "text",
                    "primaryKey": false,
                    "notNull": true
                }
            },
            "indexes": {},
            "foreignKeys": {},
            "compositePrimaryKeys": {},
            "uniqueConstraints": {
                "provinces_color_unique": {
                    "name": "provinces_color_unique",
                    "nullsNotDistinct": false,
                    "columns": ["color"]
                }
            },
            "policies": {},
            "checkConstraints": {},
            "isRLSEnabled": false
        }
    },
    "enums": {},
    "schemas": {},
    "sequences": {},
    "roles": {},
    "policies": {},
    "views": {},
    "_meta": {
        "columns": {},
        "schemas": {},
        "tables": {}
    }
}
